python_whois_extended-0.7.12.dist-info/METADATA
python_whois_extended-0.7.12.dist-info/RECORD
python_whois_extended-0.7.12.dist-info/WHEEL
python_whois_extended-0.7.12.dist-info/top_level.txt
whois/_1_query.py
whois/_2_parse.py
whois/_3_adjust.py
whois/__init__.py
whois/tld_regexpr.py
