Metadata-Version: 1.1
Name: python-whois-extended
Version: 0.7.12
Summary: Python module/library for retrieving WHOIS information of domains. Able to extract data for all the popular TLDs (com, net, org, uk, pl, ru, lv, jp, co_jp, de, at, eu, biz, info, name, us, co, me, be, nz, cz, it, fr, kg, vc, fm, tv, edu, ca)
Home-page: https://github.com/gen1us2k/python-whois/
Author: Andrew Minkin and DDarko.org
Author-email: minkin.andrew@gmail.com, ddarko@ddarko.org
License: MIT http://www.opensource.org/licenses/mit-license.php
Keywords: Python,WHOIS,TLD,domain,expiration,registrar
Platform: any
Classifier: License :: OSI Approved :: MIT License
Classifier: Intended Audience :: Developers
Classifier: Environment :: Console
Classifier: Programming Language :: Python
Classifier: Programming Language :: Python :: 2.5
Classifier: Programming Language :: Python :: 2.6
Classifier: Programming Language :: Python :: 2.7
Classifier: Programming Language :: Python :: 3
Classifier: Programming Language :: Python :: 3.0
Classifier: Programming Language :: Python :: 3.1
Classifier: Programming Language :: Python :: 3.2
Classifier: Topic :: Internet
Classifier: Topic :: Software Development :: Libraries :: Python Modules
